demo_poetry/__init__.py
demo_poetry-0.1.0.dist-info/WHEEL
demo_poetry-0.1.0.dist-info/METADATA
demo_poetry-0.1.0.dist-info/RECORD
